{"hash":"01f5ad12bb53d72cffaa0e13a520ff82631e9790","data":{"session":{"speaker":"Leandro Melendez","speaker2":"","bio":"Leandro Melendez is a performance testing manager providing testing and consulting services to worldwide companies. He has over 20 years of experience in IT and over 10 in the performance testing practice where he served multiple S&P500 customers all over the USA, Mexico, Canada, Brazil, India, Austria, etc. Author of the popular performance testing blog Señor Performo (www.srperf.com) where he curates a diverse set of learning material for performance testers and engineers. He is the producer and host of the Spanish language version of the PerfBytes podcast and the Señor Performo learning YouTube channels. He is an international public speaker participating in multiple conferences, events and webinars, with keynotes, workshops and multiple talks on his belt. And last, author of \"The Hitchhikers Guide To Load Testing Projects\", a fun walkthrough that will guide you through the phases or levels of an IT load testing project.","bio2":"","title":"Performance and Beyond","abstract":"Performance testing has been moving and jumping around with Site Reliability, SETs, and many new methodologies arising like Agile, DevOps, Scrum Continuous, and many more.\n\nBut sadly not many organizations or professionals have been able to move and evolve with the new set of requirements for the performance engineer.\n\nLearn about why the trade of the performance scripter is dying (or at least diminishing), why it is not suitable anymore for these modern times, and how to tackle the new challenge of not only testing our system's performance... But assuring it!","time":"12:45 - 1:45","room":"Great Hall 1 & 2","linkedin":"https://www.linkedin.com/in/leandromelendez/","twitter":"https://twitter.com/SrPerf","website":"http://www.srperf.com/","linkedin2":"","twitter2":"","website2":"","youtube":"https://www.youtube.com/channel/UCSd5XYudbkojiPKNNKmma8w","youtube2":""}},"context":{}}